ez_parallel/__init__.py
ez_parallel/__main__.py
ez_parallel/misc.py
ez_parallel/multiprocess.py
ez_parallel/py.typed
ez_parallel-0.1.11.dist-info/entry_points.txt
ez_parallel-0.1.11.dist-info/LICENSE
ez_parallel-0.1.11.dist-info/WHEEL
ez_parallel-0.1.11.dist-info/METADATA
ez_parallel-0.1.11.dist-info/RECORD
