Metadata-Version: 2.1
Name: ez-parallel
Version: 0.1.11
Summary: Easy Parallel Multiprocessing
Home-page: https://github.com/j-rossi-nl/ez-parallel
License: MIT
Author: Julien Rossi
Author-email: j.rossi@uva.nl
Requires-Python: >=3.7,<4.0
Classifier: Development Status :: 3 - Alpha
Classifier: Intended Audience :: Developers
Classifier: License :: OSI Approved :: MIT License
Classifier: Operating System :: OS Independent
Classifier: Programming Language :: Python :: 3
Classifier: Programming Language :: Python :: 3.7
Classifier: Programming Language :: Python :: 3.8
Classifier: Programming Language :: Python :: 3.9
Classifier: Topic :: Software Development :: Libraries :: Python Modules
Classifier: Typing :: Typed
Requires-Dist: click (>=8,<8.1)
Requires-Dist: coverage (>=6.0b1)
Requires-Dist: importlib_metadata (>=1.6.0,<2.0.0); python_version < "3.8"
Requires-Dist: rich (>=9.8.2,<10.0.0)
Requires-Dist: typer (>=0.4,<1.0)
Project-URL: Repository, https://github.com/j-rossi-nl/ez-parallel
